README.md
README.rst
setup.py
salary_timetracker_sqlite.egg-info/PKG-INFO
salary_timetracker_sqlite.egg-info/SOURCES.txt
salary_timetracker_sqlite.egg-info/dependency_links.txt
salary_timetracker_sqlite.egg-info/entry_points.txt
salary_timetracker_sqlite.egg-info/requires.txt
salary_timetracker_sqlite.egg-info/top_level.txt
timetracker_sqlite/__init__.py
timetracker_sqlite/config.py
timetracker_sqlite/main.py
timetracker_sqlite/utils.py