Metadata-Version: 1.1
Name: salary-timetracker-sqlite
Version: 0.2
Summary: A simple and easy timetracker for loging working hours with sqlite db and automatic wage calculation.
Home-page: http://github.com/dalay/salary-timetracker-sqlite
Author: Alexandr Jurow
Author-email: pythonwayru@gmail.com
License: GPL
Download-URL: https://github.com/dalay/salary-timetracker-sqlite/archive/v0.2.tar.gz
Keywords: timetracker,salary,freelance,sqlite
Platform: UNKNOWN
Classifier: Development Status :: 4 - Beta
Classifier: Environment :: Console
Classifier: Intended Audience :: Developers
Classifier: License :: OSI Approved :: GNU General Public License (GPL)
Classifier: Operating System :: POSIX :: Linux
Classifier: Programming Language :: Python
Classifier: Programming Language :: Python :: 3.4
Classifier: Programming Language :: Python :: 3.5
Classifier: Programming Language :: Python :: 3.6
Classifier: Programming Language :: Python :: 3.7
Classifier: Topic :: Utilities
